app/__init__.py
app/apimodels.py
app/exporters.py
app/exportmanager.py
app/main.py
app/options.py
app/retriever.py
app/utils.py
youtube_playlist_exporter-0.3.0.dist-info/licenses/LICENSE
youtube_playlist_exporter-0.3.0.dist-info/METADATA
youtube_playlist_exporter-0.3.0.dist-info/WHEEL
youtube_playlist_exporter-0.3.0.dist-info/entry_points.txt
youtube_playlist_exporter-0.3.0.dist-info/top_level.txt
youtube_playlist_exporter-0.3.0.dist-info/RECORD
