Metadata-Version: 2.4
Name: youtube-playlist-exporter
Version: 0.3.0
Summary: A CLI for exporting YouTube playlists' data to local files
Author-email: Dean Gurvitz <deansg@gmail.com>
License-Expression: Apache-2.0
Project-URL: homepage, https://github.com/deansg/youtube-playlist-exporter
Keywords: CLI,YouTube
Requires-Python: >=3.10
License-File: LICENSE
Requires-Dist: aiohttp==3.11.16
Requires-Dist: dataclasses-json>=0.6.7
Requires-Dist: google-auth-oauthlib>=1.2.2
Requires-Dist: typer>=0.15.2
Dynamic: license-file
